create_doc/__init__.py
create_doc/__main__.py
create_doc/analyze_module_dependencies.py
create_doc/analyze_with_gpt.py
create_doc/cli.py
create_doc/create_doc.py
create_doc/utils.py
create_doc-0.1.6.dist-info/AUTHORS.md
create_doc-0.1.6.dist-info/LICENSE
create_doc-0.1.6.dist-info/METADATA
create_doc-0.1.6.dist-info/WHEEL
create_doc-0.1.6.dist-info/entry_points.txt
create_doc-0.1.6.dist-info/top_level.txt
create_doc-0.1.6.dist-info/RECORD
