Metadata-Version: 2.1
Name: create-doc
Version: 0.1.6
Summary: Generate project documentation using GPT.
Home-page: https://github.com/Nomendi6/create_doc
Author: Ivan Vrbovčan
Author-email: ivan.vrbovcan@nomendi6.com
License: MIT license
Keywords: create_doc
Classifier: Development Status :: 2 - Pre-Alpha
Classifier: Intended Audience :: Developers
Classifier: License :: OSI Approved :: MIT License
Classifier: Natural Language :: English
Classifier: Programming Language :: Python :: 3
Classifier: Programming Language :: Python :: 3.6
Classifier: Programming Language :: Python :: 3.7
Classifier: Programming Language :: Python :: 3.8
Requires-Python: >=3.6
License-File: LICENSE
License-File: AUTHORS.md
Requires-Dist: Click (>=7.0)
Requires-Dist: openai
Requires-Dist: python-dotenv
Requires-Dist: tiktoken
